shapsplain/__init__.py
shapsplain/forest.py
shapsplain/gradient.py
shapsplain/importers.py
shapsplain/node.py
shapsplain/represent.py
shapsplain/scikit.py
shapsplain/shap.py
shapsplain/utils.py
shapsplain-0.3.0.dist-info/METADATA
shapsplain-0.3.0.dist-info/WHEEL
shapsplain-0.3.0.dist-info/top_level.txt
shapsplain-0.3.0.dist-info/RECORD
