Metadata-Version: 2.1
Name: shapsplain
Version: 0.3.0
Summary: Wrapper for shapley explanations
Home-page: http://bigml.com/
Author: BigML Team
Author-email: team@bigml.com
Requires-Dist: numba <0.59,>=0.58
Requires-Dist: numpy <1.27,>=1.26.3
Requires-Dist: scikit-learn <1.4.1,>=1.4.0
Requires-Dist: tensorflow <2.16,>=2.15 ; sys_platform != "Darwin" or platform_machine != "arm64"
Requires-Dist: tensorflow-macos <2.16,>=2.15 ; sys_platform == "Darwin" and platform_machine == "arm64"
